rag_demo/__init__.py
rag_demo/__main__.py
rag_demo/app.py
rag_demo/app.tcss
rag_demo/db.py
rag_demo/dirs.py
rag_demo/logic.py
rag_demo/markdown.py
rag_demo/modes/__init__.py
rag_demo/modes/_logic_provider.py
rag_demo/modes/chat.py
rag_demo/modes/chat.tcss
rag_demo/modes/config.py
rag_demo/modes/config.tcss
rag_demo/modes/help.py
rag_demo/modes/help.tcss
rag_demo/py.typed
rag_demo/widgets/__init__.py
rag_demo/widgets/escapable_input.py
jehoctor_rag_demo-0.2.0.dist-info/WHEEL
jehoctor_rag_demo-0.2.0.dist-info/entry_points.txt
jehoctor_rag_demo-0.2.0.dist-info/METADATA
jehoctor_rag_demo-0.2.0.dist-info/RECORD
