Metadata-Version: 2.3
Name: jehoctor-rag-demo
Version: 0.2.0
Summary: Chat with Wikipedia
Author: James Hoctor
Author-email: James Hoctor <JEHoctor@protonmail.com>
Requires-Dist: aiosqlite==0.21.0
Requires-Dist: chromadb>=1.3.4
Requires-Dist: datasets>=4.4.1
Requires-Dist: httpx>=0.28.1
Requires-Dist: huggingface-hub>=0.36.0
Requires-Dist: langchain>=1.0.5
Requires-Dist: langchain-anthropic>=1.0.2
Requires-Dist: langchain-community>=0.4.1
Requires-Dist: langchain-huggingface>=1.1.0
Requires-Dist: langchain-ollama>=1.0.0
Requires-Dist: langchain-openai>=1.0.2
Requires-Dist: langgraph-checkpoint-sqlite>=3.0.1
Requires-Dist: llama-cpp-python>=0.3.16
Requires-Dist: nvidia-ml-py>=13.590.44
Requires-Dist: ollama>=0.6.0
Requires-Dist: platformdirs>=4.5.0
Requires-Dist: psutil>=7.1.3
Requires-Dist: py-cpuinfo>=9.0.0
Requires-Dist: pydantic>=2.12.4
Requires-Dist: pyperclip>=1.11.0
Requires-Dist: textual>=6.5.0
Requires-Dist: typer>=0.20.0
Requires-Python: >=3.12
